llama_index/extractors/marvin/__init__.py
llama_index/extractors/marvin/base.py
llama_index_extractors_marvin-0.4.1.dist-info/METADATA
llama_index_extractors_marvin-0.4.1.dist-info/WHEEL
llama_index_extractors_marvin-0.4.1.dist-info/licenses/LICENSE
llama_index_extractors_marvin-0.4.1.dist-info/RECORD
