Metadata-Version: 2.4
Name: llama-index-extractors-marvin
Version: 0.4.1
Summary: llama-index extractors marvin integration
Author-email: Your Name <you@example.com>
License-Expression: MIT
License-File: LICENSE
Requires-Python: <4.0,>=3.9
Requires-Dist: llama-index-core<0.15,>=0.13.0
Requires-Dist: marvin<3,>=2.1.3
